linkkit/__init__.py
linkkit/h2client.py
linkkit/linkkit.py
linksdktest/__init__.py
linksdktest/common/__init__.py
linksdktest/common/method.py
linksdktest/common/var.py
aliyun_iot_linkkit-1.2.2.dist-info/LICENSE
aliyun_iot_linkkit-1.2.2.dist-info/METADATA
aliyun_iot_linkkit-1.2.2.dist-info/WHEEL
aliyun_iot_linkkit-1.2.2.dist-info/top_level.txt
aliyun_iot_linkkit-1.2.2.dist-info/RECORD
