Metadata-Version: 2.1
Name: aliyun-iot-linkkit
Version: 1.2.2
Summary: Aliyun IoT Linkkit SDK for Python
Home-page: UNKNOWN
Author: Aliyun IoT Linkkit Python SDK
Author-email: 
License: UNKNOWN
Platform: UNKNOWN
Classifier: Programming Language :: Python :: 3
Classifier: License :: OSI Approved :: Apache Software License
Classifier: Operating System :: OS Independent
Requires-Dist: paho-mqtt
Requires-Dist: hyper
Requires-Dist: crcmod
